cove_unified_logs/__init__.py
cove_unified_logs/cloud_logger.py
cove_unified_logs/console_logger.py
cove_unified_logs/log_consumer.py
cove_unified_logs/log_producer.py
cove_unified_logs/logger.py
cove_unified_logs/middleware.py
cove_unified_logs/singleton.py
cove_unified_logs/unified_logger.py
cove_unified_logs-0.2.2.dist-info/LICENSE
cove_unified_logs-0.2.2.dist-info/METADATA
cove_unified_logs-0.2.2.dist-info/WHEEL
cove_unified_logs-0.2.2.dist-info/top_level.txt
cove_unified_logs-0.2.2.dist-info/RECORD
