Metadata-Version: 2.1
Name: cove-unified-logs
Version: 0.2.2
Summary: A Python logging library for unified logging across AWS Lambda, Django, and Google Cloud servers. Logs are asynchronously pushed to AWS CloudWatch.
Home-page: https://github.com/Cove-Identity/cove-unified-logs
Author: Coveidentity Tech Private Limited
Author-email: sarvpriye.soni@coveidentity.com
License: UNKNOWN
Platform: UNKNOWN
Classifier: Development Status :: 3 - Alpha
Classifier: Intended Audience :: Developers
Classifier: License :: OSI Approved :: MIT License
Classifier: Programming Language :: Python :: 3
Classifier: Programming Language :: Python :: 3.6
Classifier: Programming Language :: Python :: 3.7
Classifier: Programming Language :: Python :: 3.8
License-File: LICENSE
Requires-Dist: boto3
Requires-Dist: python-json-logger
Requires-Dist: redis
